{
    "config": {
        "postsPerPage": "6",
        "tagsPostsPerPage": "6",
        "authorsPostsPerPage": "6",
        "excerptLength": 45,
        "logo": "media/website/CEXAsset-31.png"
    },
    "customConfig": {
        "pageMargin": "6vmin",
        "pageWidth": "1280px",
        "entryWidth": "60rem",
        "frontSource": "post",
        "frontPost": 4,
        "frontGallery": true,
        "slider": true,
        "sliderSource": "tag",
        "sliderIndicator": "",
        "sliderItemsAmount": "2",
        "sliderItemExcluded": "",
        "sliderItemOffset": "",
        "sliderItemOrdering": "desc",
        "includeFeaturedInPosts": true,
        "sliderTitle": true,
        "sliderMainTag": true,
        "sliderAuthor": true,
        "sliderDate": true,
        "sliderImageHeight": "55vh",
        "sliderLoop": false,
        "sliderSpeed": "6",
        "sliderDraggable": true,
        "sliderDraggFree": false,
        "sliderAutoplay": true,
        "sliderAutoplayTimeout": "6000",
        "sliderProgressBar": true,
        "sliderCounter": true,
        "sidebarSticky": false,
        "tagsFeaturedImage": true,
        "submenu": "auto",
        "submenuWidth": "240",
        "mobilemenu": "sidebar",
        "mobilemenuExpandableSubmenus": true,
        "cardsMainTag": true,
        "cardsAuthor": true,
        "cardsDate": true,
        "colorScheme": "light",
        "whiteLightColor": "#FFFFFF",
        "blackLightColor": "#000000",
        "darkLightColor": "#161616",
        "grayLightColor": "#536162",
        "lightLightColor": "#D5D5D5",
        "lighterLightColor": "#F6F6F6",
        "pageLightBg": "#FFFFFF",
        "primaryLightColor": "#FF5151",
        "textLightColor": "#262626",
        "headingsLightColor": "#262626",
        "linkLightColor": "#262626",
        "linkLightHoverColor": "#FF5151",
        "codeLightColor": "#FF5151",
        "whiteDarkColor": "#161618",
        "blackDarkColor": "#FFFFFF",
        "darkDarkColor": "#CECBCB",
        "grayDarkColor": "#9D9D9D",
        "lightDarkColor": "#373737",
        "lighterDarkColor": "#212124",
        "pageDarkBg": "#181818",
        "primaryDarkColor": "#FFC074",
        "textDarkColor": "#BFBFBF",
        "headingsDarkColor": "#CECBCB",
        "linkDarkColor": "#CECBCB",
        "linkDarkHoverColor": "#FFC074",
        "codeDarkColor": "#FFC074",
        "fontFamily": "font-pair-0",
        "minFontSize": "1.1",
        "maxFontSize": "1.25",
        "fontNormalWeight": "400",
        "fontBoldWeight": "700",
        "lineHeight": "1.6",
        "fontHeadignsWeight": "700",
        "fontHeadingsTransform": "uppercase",
        "shareFacebook": false,
        "shareTwitter": true,
        "shareTwitterName": "",
        "sharePinterest": false,
        "shareMix": true,
        "shareLinkedin": true,
        "shareBuffer": false,
        "shareWhatsApp": true,
        "sharePocket": false,
        "commentDisqusShortname": "",
        "createSearchPage": false,
        "searchId": "",
        "searchParam": "q",
        "footerNewsletter": "disabled",
        "footerNewsletterMailchimpURL": "",
        "footerNewsletterFormCode": "<form>...</form>",
        "copyrightText": "Powered by The Source Code",
        "socialButtons": false,
        "socialFacebook": "",
        "socialTwitter": "",
        "socialInstagram": "",
        "socialLinkedin": "",
        "socialVimeo": "",
        "socialPinterest": "",
        "socialYoutube": "",
        "galleryItemGap": "0.25rem",
        "galleryLightboxStyle": "pswp--dark",
        "galleryLightboxOpacity": "0.7",
        "galleryAdvanced": false,
        "galleryCounter": true,
        "galleryZoom": true,
        "galleryFullscreen": true,
        "galleryShare": true,
        "galleryClose": true,
        "galleryArrows": true,
        "galleryPreloader": true,
        "galleryCloseOnScroll": true,
        "galleryArrowKeys": true,
        "codeMaxHeight": "100%",
        "pagePrefetching": false,
        "formatDate": "DD.MM.YYYY",
        "formatDateCustom": "HH:mm:ss YY/MM/DD",
        "lazyLoadEffect": "fadein",
        "faviconUpload": "",
        "faviconExtension": "image/x-icon"
    },
    "postConfig": {
        "sidebarPosition": "right",
        "displayMainTag": "0",
        "displayAuthor": "0",
        "displayDate": "0",
        "displayUpdatedDate": "0",
        "displayShareButtons": "0",
        "displayTags": "0",
        "displayPostNavigation": "0",
        "displayFeaturedImage": "0",
        "displayAuthorBio": "0",
        "displayComments": 0,
        "displayRelatedPosts": "0"
    },
    "defaultTemplates": {
        "post": ""
    }
}